netrun/rbac/__init__.py
netrun/rbac/dependencies_legacy.py
netrun/rbac/exceptions.py
netrun/rbac/models_legacy.py
netrun/rbac/policies.py
netrun/rbac/py.typed
netrun/rbac/tenant.py
netrun/rbac/testing_legacy.py
netrun/rbac/dependencies/__init__.py
netrun/rbac/dependencies/share.py
netrun/rbac/dependencies/team.py
netrun/rbac/dependencies/tenant.py
netrun/rbac/isolation/__init__.py
netrun/rbac/isolation/application.py
netrun/rbac/isolation/base.py
netrun/rbac/isolation/hybrid.py
netrun/rbac/isolation/rls.py
netrun/rbac/middleware/__init__.py
netrun/rbac/middleware/isolation.py
netrun/rbac/middleware/security.py
netrun/rbac/middleware/stack.py
netrun/rbac/middleware/tenant.py
netrun/rbac/migrations/__init__.py
netrun/rbac/migrations/helpers.py
netrun/rbac/migrations/rls_generator.py
netrun/rbac/models/__init__.py
netrun/rbac/models/enums.py
netrun/rbac/models/membership.py
netrun/rbac/models/mixins.py
netrun/rbac/models/resource_share.py
netrun/rbac/models/team.py
netrun/rbac/models/tenant.py
netrun/rbac/services/__init__.py
netrun/rbac/services/membership_service.py
netrun/rbac/services/share_service.py
netrun/rbac/services/team_service.py
netrun/rbac/services/tenant_query.py
netrun/rbac/services/tenant_service.py
netrun/rbac/tenancy/__init__.py
netrun/rbac/tenancy/config.py
netrun/rbac/tenancy/context.py
netrun/rbac/tenancy/exceptions.py
netrun/rbac/testing/__init__.py
netrun/rbac/testing/fixtures.py
netrun/rbac/testing/isolation_tests.py
netrun/rbac/tests/__init__.py
netrun/rbac/tests/conftest.py
netrun/rbac/tests/test_tenant_isolation.py
netrun_rbac-3.0.0.dist-info/METADATA
netrun_rbac-3.0.0.dist-info/WHEEL
netrun_rbac-3.0.0.dist-info/RECORD
