Metadata-Version: 2.4
Name: netrun-rbac
Version: 3.0.0
Summary: Multi-tenant Role-Based Access Control (RBAC) with PostgreSQL Row-Level Security (RLS), Hierarchical Teams, Resource Sharing, and Isolation Testing
Project-URL: Homepage, https://netrunsystems.com
Project-URL: Documentation, https://github.com/netrunsystems/netrun-service-library
Project-URL: Repository, https://github.com/netrunsystems/netrun-service-library
Project-URL: Issues, https://github.com/netrunsystems/netrun-service-library/issues
Author-email: Netrun Systems <support@netrunsystems.com>
License: MIT
Keywords: authorization,contract-testing,fastapi,iso27001,multi-tenant,postgres,rbac,resource-sharing,rls,security,soc2,team-hierarchy,tenant-isolation
Classifier: Development Status :: 4 - Beta
Classifier: Framework :: FastAPI
Classifier: Intended Audience :: Developers
Classifier: License :: OSI Approved :: MIT License
Classifier: Programming Language :: Python :: 3
Classifier: Programming Language :: Python :: 3.10
Classifier: Programming Language :: Python :: 3.11
Classifier: Programming Language :: Python :: 3.12
Classifier: Topic :: Security
Classifier: Topic :: Software Development :: Libraries :: Python Modules
Requires-Python: >=3.10
Requires-Dist: fastapi>=0.100.0
Requires-Dist: netrun-core>=1.0.0
Requires-Dist: pydantic>=2.0.0
Requires-Dist: sqlalchemy>=2.0.0
Requires-Dist: starlette>=0.27.0
Provides-Extra: dev
Requires-Dist: asyncpg>=0.29.0; extra == 'dev'
Requires-Dist: black>=23.0.0; extra == 'dev'
Requires-Dist: mypy>=1.0.0; extra == 'dev'
Requires-Dist: pytest-asyncio>=0.21.0; extra == 'dev'
Requires-Dist: pytest-cov>=4.0.0; extra == 'dev'
Requires-Dist: pytest>=7.0.0; extra == 'dev'
Requires-Dist: ruff>=0.1.0; extra == 'dev'
